pyqt_font_dialog/__init__.py
pyqt_font_dialog/fontDialog.py
pyqt_font_dialog/fontItemWidget.py
pyqt_font_dialog/fontWidget.py
pyqt_font_dialog/sizeWidget.py
pyqt_font_dialog/styleWidget.py
pyqt_font_dialog-0.0.14.dist-info/LICENSE
pyqt_font_dialog-0.0.14.dist-info/METADATA
pyqt_font_dialog-0.0.14.dist-info/WHEEL
pyqt_font_dialog-0.0.14.dist-info/top_level.txt
pyqt_font_dialog-0.0.14.dist-info/RECORD
