Metadata-Version: 2.1
Name: pyqt-font-dialog
Version: 0.0.14
Summary: PyQt font dialog and widget
Home-page: https://github.com/yjg30737/pyqt-font-dialog.git
Author: Jung Gyu Yoon
Author-email: yjg30737@gmail.com
License: MIT
License-File: LICENSE
Requires-Dist: PyQt5 (>=5.8)
